pyptz/__init__.py
pyptz/onvif_control.py
pyptz/sunapi_control.py
pyptz/vapix_control.py
pyptz-0.1.8.dist-info/LICENSE
pyptz-0.1.8.dist-info/METADATA
pyptz-0.1.8.dist-info/WHEEL
pyptz-0.1.8.dist-info/top_level.txt
pyptz-0.1.8.dist-info/RECORD
