Metadata-Version: 2.1
Name: pyptz
Version: 0.1.8
Summary: PTZ Camera Control using Python
Home-page: https://github.com/jahongir7174/PyPTZ
Author: Jahongir Yunusov
License: MIT
Keywords: ONVIF,VAPIX,SUNAPI
Classifier: Programming Language :: Python :: 3
Classifier: License :: OSI Approved :: MIT License
Classifier: Operating System :: OS Independent
Requires-Python: >=3.6
License-File: LICENSE
Requires-Dist: urllib3 ==1.26.18
Requires-Dist: requests ==2.31.0
Requires-Dist: onvif-zeep ==0.2.12
Requires-Dist: beautifulsoup4 ==4.12.3
